pyatb/__init__.py
pyatb/_typing.py
pyatb/constants.py
pyatb/init_tb.py
pyatb/interface_python.cpython-38-x86_64-linux-gnu.so
pyatb/main.py
pyatb/parallel.py
pyatb/timer.py
pyatb/berry/__init__.py
pyatb/berry/ahc.py
pyatb/berry/anc.py
pyatb/berry/berry_curvature.py
pyatb/berry/berry_curvature_dipole.py
pyatb/berry/chern_num.py
pyatb/berry/chirality.py
pyatb/berry/cpge.py
pyatb/berry/drude_weight.py
pyatb/berry/optical_conductivity.py
pyatb/berry/orbital_magnetization.py
pyatb/berry/pockels.py
pyatb/berry/polarization.py
pyatb/berry/second_order_static.py
pyatb/berry/shc.py
pyatb/berry/shg.py
pyatb/berry/shift_current.py
pyatb/berry/wilson_loop.py
pyatb/easy_use/__init__.py
pyatb/easy_use/input_generator.py
pyatb/easy_use/stru_analyzer.py
pyatb/fermi/__init__.py
pyatb/fermi/band_structure.py
pyatb/fermi/bandunfolding.py
pyatb/fermi/bandunfolding_spin_texture.py
pyatb/fermi/fat_band.py
pyatb/fermi/fermi_energy.py
pyatb/fermi/fermi_surface.py
pyatb/fermi/find_nodes.py
pyatb/fermi/jdos.py
pyatb/fermi/pdos.py
pyatb/fermi/reduce_basis_check.py
pyatb/fermi/spin_texture.py
pyatb/fermi/surface_state.py
pyatb/fermi/surface_state_old_version.py
pyatb/integration/__init__.py
pyatb/integration/adaptive_integral.py
pyatb/integration/generator.py
pyatb/integration/grid_integrate_3d.py
pyatb/io/__init__.py
pyatb/io/abacus_read_stru.py
pyatb/io/abacus_read_xr.py
pyatb/io/default_input.py
pyatb/io/input.py
pyatb/io/wannier90_read_tb.py
pyatb/kpt/__init__.py
pyatb/kpt/kpoint_generator.py
pyatb/kpt/kpoint_tools.py
pyatb/tb/__init__.py
pyatb/tb/multixr.py
pyatb/tb/solver.py
pyatb/tb/tb.py
pyatb/tools/__init__.py
pyatb/tools/band.py
pyatb/tools/dosplot.py
pyatb/tools/plot_utils.py
pyatb/tools/smearing.py
pyatb/transport/__init__.py
pyatb/transport/boltz_transport.py
pyatb.libs/libgfortran-91cc3cb1.so.3.0.0
pyatb.libs/libgomp-a34b3233.so.1.0.0
pyatb.libs/liblapacke-7659a628.so.3.4.2
pyatb-1.1.2.dist-info/LICENSE
pyatb-1.1.2.dist-info/METADATA
pyatb-1.1.2.dist-info/WHEEL
pyatb-1.1.2.dist-info/entry_points.txt
pyatb-1.1.2.dist-info/top_level.txt
pyatb-1.1.2.dist-info/RECORD
pyatb-1.1.2.dist-info/sboms/auditwheel.cdx.json
