Metadata-Version: 2.1
Name: pyatb
Version: 1.1.2
Summary: This is the pyatb module.
Home-page: https://github.com/pyatb/pyatb
Author: PYATB Developer
Author-email: jingan@mail.ustc.edu.cn
License: GPL v3.0
License-File: LICENSE
Requires-Dist: numpy>=1.17.0
Requires-Dist: scipy>=1.5.0
Requires-Dist: mpi4py>=3.1.0
Requires-Dist: matplotlib>=2.2.2
Requires-Dist: ase
